cv/__init__.py
cv/admin.py
cv/apps.py
cv/constants.py
cv/context_processors.py
cv/forms.py
cv/settings.py
cv/signals.py
cv/urls.py
cv/utils.py
cv/views.py
cv/migrations/0001_initial.py
cv/migrations/0002_auto_20180924_0247.py
cv/migrations/0003_auto_20180928_0228.py
cv/migrations/0004_auto_20181002_0244.py
cv/migrations/0005_auto_20181002_0247.py
cv/migrations/0006_auto_20181002_1602.py
cv/migrations/0007_auto_20181002_1606.py
cv/migrations/0008_auto_20181003_1843.py
cv/migrations/__init__.py
cv/models/__init__.py
cv/models/base.py
cv/models/files.py
cv/models/managers.py
cv/models/publications.py
cv/models/works.py
cv/static/cv/cv-forms.css
cv/static/cv/cv-main.css
cv/templates/cv/base.html
cv/templates/cv/contact.html
cv/templates/cv/cv.html
cv/templates/cv/skeleton.html
cv/templates/cv/citations/article.bib
cv/templates/cv/citations/article.ris
cv/templates/cv/citations/book.bib
cv/templates/cv/citations/book.ris
cv/templates/cv/citations/report.bib
cv/templates/cv/citations/report.ris
cv/templates/cv/citations/talk.bib
cv/templates/cv/citations/talk.ris
cv/templates/cv/details/_cv_detail_base.html
cv/templates/cv/details/article_detail.html
cv/templates/cv/details/book_detail.html
cv/templates/cv/details/dataset_detail.html
cv/templates/cv/details/report_detail.html
cv/templates/cv/details/talk_detail.html
cv/templates/cv/forms/_article_base.html
cv/templates/cv/forms/_base.html
cv/templates/cv/forms/_book_base.html
cv/templates/cv/forms/_publication_base.html
cv/templates/cv/forms/_publication_field.html
cv/templates/cv/forms/article.html
cv/templates/cv/forms/article_add_form.html
cv/templates/cv/forms/article_edit_form.html
cv/templates/cv/forms/book.html
cv/templates/cv/forms/book_add_form.html
cv/templates/cv/forms/chapter.html
cv/templates/cv/forms/course.html
cv/templates/cv/forms/cv_add_form.html
cv/templates/cv/forms/cv_confirm_delete.html
cv/templates/cv/forms/cv_edit_form.html
django_vitae-0.1.0.dist-info/METADATA
django_vitae-0.1.0.dist-info/RECORD
django_vitae-0.1.0.dist-info/WHEEL
django_vitae-0.1.0.dist-info/top_level.txt
