Metadata-Version: 2.1
Name: django-vitae
Version: 0.1.0
Summary: A CV generator built for the Django web framework.
Home-page: https://github.com/mikebader/django-vitae
Author: Michael Bader
Author-email: michaeldmbader@gmail.com
License: BSD Three Clause
Platform: UNKNOWN
Classifier: Development Status :: 3 - Alpha
Classifier: Framework :: Django
Classifier: Intended Audience :: Science/Research
Classifier: License :: OSI Approved :: BSD License
Classifier: Programming Language :: Python :: 3
Requires-Dist: django (>=1.11)
Requires-Dist: markdown (>=2.6.11)
Requires-Dist: citeproc-py (>=0.4.0)
Requires-Dist: citeproc-py-styles (>=0.1.1)
Requires-Dist: django-widgets (>=-0.1.16)
Requires-Dist: reportlab (<4,>=3.5.8)
